storefact/__init__.py
storefact/_boto.py
storefact/_compat.py
storefact/_hstores.py
storefact/_store_creation.py
storefact/_store_decoration.py
storefact/_urls.py
storefact/_version.py
storefact-0.11.0.dist-info/AUTHORS.rst
storefact-0.11.0.dist-info/LICENSE
storefact-0.11.0.dist-info/METADATA
storefact-0.11.0.dist-info/WHEEL
storefact-0.11.0.dist-info/top_level.txt
storefact-0.11.0.dist-info/RECORD
