Metadata-Version: 2.1
Name: storefact
Version: 0.11.0
Summary: A factory for simplekv-Store-based storage classes. Takes configuration values and returns a simplekv-Store
Home-page: https://github.com/blue-yonder/storefact
Author: Felix Marczinowski
Author-email: felix.marczinowski@blue-yonder.com
Classifier: Intended Audience :: Developers
Classifier: License :: OSI Approved :: BSD License
Classifier: Operating System :: Unix
Classifier: Operating System :: POSIX
Classifier: Operating System :: Microsoft :: Windows
Classifier: Programming Language :: Python
Classifier: Programming Language :: Python :: 2.7
Classifier: Programming Language :: Python :: 3.5
Classifier: Programming Language :: Python :: 3.6
Classifier: Programming Language :: Python :: 3.9
Classifier: Programming Language :: Python :: Implementation :: CPython
Classifier: Topic :: Utilities
License-File: LICENSE
License-File: AUTHORS.rst
Requires-Dist: simplekv (>=0.13.1)
Requires-Dist: uritools
Requires-Dist: toolz
Provides-Extra: azure
Requires-Dist: azure-storage-blob ; extra == 'azure'
Provides-Extra: s3
Requires-Dist: boto ; extra == 's3'
